setup.py
client/__init__.py
client/client.py
client/client/__init__.py
client/client/add_contact.py
client/client/database.py
client/client/del_contact.py
client/client/main_window.py
client/client/main_window_conv.py
client/client/start_dialog.py
client/client/transport.py
client/common/__init__.py
client/common/common.py
client/common/decos.py
client/common/descryptors.py
client/common/errors.py
client/common/meta_classes.py
client/common/variables.py
client/logs/__init__.py
client/logs/client_log_config.py
client/logs/server_log_config.py
mess_client_proj_roma_june.egg-info/PKG-INFO
mess_client_proj_roma_june.egg-info/SOURCES.txt
mess_client_proj_roma_june.egg-info/dependency_links.txt
mess_client_proj_roma_june.egg-info/requires.txt
mess_client_proj_roma_june.egg-info/top_level.txt